generic_crawler/__init__.py
generic_crawler/actions.py
generic_crawler/config.py
generic_crawler/core.py
generic_crawler/sample.py
generic_crawler_sdk-0.1.11.dist-info/LICENSE.txt
generic_crawler_sdk-0.1.11.dist-info/METADATA
generic_crawler_sdk-0.1.11.dist-info/WHEEL
generic_crawler_sdk-0.1.11.dist-info/top_level.txt
generic_crawler_sdk-0.1.11.dist-info/RECORD
