Metadata-Version: 2.1
Name: generic-crawler-sdk
Version: 0.1.11
Summary: Generic Crawler SDK
Home-page: UNKNOWN
Author: Umut Alihan Dikel
Author-email: alihan.dikel@turkcell.com.tr
License: UNKNOWN
Keywords: generic_crawler
Platform: UNKNOWN
Classifier: Programming Language :: Python :: 3
Classifier: Operating System :: OS Independent
Requires-Python: >=3.8
License-File: LICENSE.txt
Requires-Dist: argcomplete (==1.12.3)
Requires-Dist: asgiref (==3.5.2)
Requires-Dist: attrs (==21.4.0)
Requires-Dist: bleach (==5.0.0)
Requires-Dist: build (==0.8.0)
Requires-Dist: certifi (==2022.5.18.1)
Requires-Dist: charset-normalizer (==2.0.12)
Requires-Dist: click (==8.1.3)
Requires-Dist: colorlog (==6.6.0)
Requires-Dist: commonmark (==0.9.1)
Requires-Dist: contextlib2 (==21.6.0)
Requires-Dist: decorator (==5.1.1)
Requires-Dist: distlib (==0.3.4)
Requires-Dist: docutils (==0.18.1)
Requires-Dist: filelock (==3.7.1)
Requires-Dist: h11 (==0.13.0)
Requires-Dist: idna (==3.3)
Requires-Dist: importlib-metadata (==4.11.4)
Requires-Dist: iniconfig (==1.1.1)
Requires-Dist: keyring (==23.5.1)
Requires-Dist: loguru (==0.6.0)
Requires-Dist: nox (==2022.1.7)
Requires-Dist: packaging (==21.3)
Requires-Dist: pep517 (==0.12.0)
Requires-Dist: pkginfo (==1.8.2)
Requires-Dist: platformdirs (==2.5.2)
Requires-Dist: pluggy (==1.0.0)
Requires-Dist: py (==1.11.0)
Requires-Dist: pydantic (==1.9.1)
Requires-Dist: Pygments (==2.12.0)
Requires-Dist: pyparsing (==3.0.9)
Requires-Dist: pytest (==7.1.2)
Requires-Dist: pytest-html (==3.2.0)
Requires-Dist: pytest-metadata (==2.0.4)
Requires-Dist: python-dotenv (==0.20.0)
Requires-Dist: PyYAML (==6.0)
Requires-Dist: readme-renderer (==35.0)
Requires-Dist: requests (==2.27.1)
Requires-Dist: requests-toolbelt (==0.9.1)
Requires-Dist: rfc3986 (==2.0.0)
Requires-Dist: rich (==12.4.4)
Requires-Dist: schema (==0.7.5)
Requires-Dist: six (==1.16.0)
Requires-Dist: toml (==0.10.2)
Requires-Dist: tomli (==2.0.1)
Requires-Dist: twine (==4.0.1)
Requires-Dist: typing-extensions (==4.2.0)
Requires-Dist: urllib3 (==1.26.9)
Requires-Dist: validators (==0.20.0)
Requires-Dist: virtualenv (==20.14.1)
Requires-Dist: webencodings (==0.5.1)
Requires-Dist: zipp (==3.8.0)
